MANIFEST.in
README.txt
setup.py
collective/__init__.py
collective.local.userlisting.egg-info/PKG-INFO
collective.local.userlisting.egg-info/SOURCES.txt
collective.local.userlisting.egg-info/dependency_links.txt
collective.local.userlisting.egg-info/entry_points.txt
collective.local.userlisting.egg-info/namespace_packages.txt
collective.local.userlisting.egg-info/not-zip-safe
collective.local.userlisting.egg-info/requires.txt
collective.local.userlisting.egg-info/top_level.txt
collective/local/__init__.py
collective/local/userlisting/__init__.py
collective/local/userlisting/configure.zcml
collective/local/userlisting/dexterity.zcml
collective/local/userlisting/interfaces.py
collective/local/userlisting/tests.py
collective/local/userlisting/userlisting.pt
collective/local/userlisting/userlisting.py
collective/local/userlisting/locales/collective.local.userlisting.pot
collective/local/userlisting/locales/update.sh
collective/local/userlisting/locales/fr/LC_MESSAGES/collective.local.userlisting.po
collective/local/userlisting/profiles/default/actions.xml
collective/local/userlisting/profiles/default/metadata.xml
collective/local/userlisting/profiles/default/propertiestool.xml
docs/HISTORY.txt
docs/INSTALL.txt
docs/LICENSE.GPL
docs/LICENSE.txt