Metadata-Version: 1.1
Name: collective.local.userlisting
Version: 1.3
Summary: Provides a view on contents that displays the list of users having a role on it.
Home-page: http://svn.plone.org/svn/collective/collective.local.userlisting
Author: Thomas Desvenain
Author-email: thomas.desvenain@gmail.com
License: GPL
Keywords: auth,project
Platform: UNKNOWN
Classifier: Framework :: Plone
Classifier: Programming Language :: Python
